decode_from_scratch/__init__.py
decode_from_scratch-1.1.dist-info/LICENSE
decode_from_scratch-1.1.dist-info/METADATA
decode_from_scratch-1.1.dist-info/WHEEL
decode_from_scratch-1.1.dist-info/top_level.txt
decode_from_scratch-1.1.dist-info/RECORD
